sloth_ci_val_github.py
sloth_ci_val_github-1.1.1.dist-info/LICENSE
sloth_ci_val_github-1.1.1.dist-info/WHEEL
sloth_ci_val_github-1.1.1.dist-info/METADATA
sloth_ci_val_github-1.1.1.dist-info/RECORD
