Metadata-Version: 2.1
Name: sloth-ci-val-github
Version: 1.1.1
Summary: GitHub validator for Sloth CI
License: MIT
Author: Constantine Molchanov
Author-email: moigagoo@live.com
Requires-Python: >=3.9,<4.0
Classifier: License :: OSI Approved :: MIT License
Classifier: Programming Language :: Python :: 3
Classifier: Programming Language :: Python :: 3.9
Classifier: Programming Language :: Python :: 3.10
Requires-Dist: sloth-ci (>=2.2,<3.0)
